MergeAccountingClient/__init__.py
MergeAccountingClient/api_client.py
MergeAccountingClient/configuration.py
MergeAccountingClient/exceptions.py
MergeAccountingClient/model_utils.py
MergeAccountingClient/rest.py
MergeAccountingClient/api/__init__.py
MergeAccountingClient/api/account_details_api.py
MergeAccountingClient/api/account_token_api.py
MergeAccountingClient/api/accounts_api.py
MergeAccountingClient/api/addresses_api.py
MergeAccountingClient/api/attachments_api.py
MergeAccountingClient/api/available_actions_api.py
MergeAccountingClient/api/balance_sheets_api.py
MergeAccountingClient/api/cash_flow_statements_api.py
MergeAccountingClient/api/company_info_api.py
MergeAccountingClient/api/contacts_api.py
MergeAccountingClient/api/credit_notes_api.py
MergeAccountingClient/api/delete_account_api.py
MergeAccountingClient/api/expenses_api.py
MergeAccountingClient/api/force_resync_api.py
MergeAccountingClient/api/generate_key_api.py
MergeAccountingClient/api/income_statements_api.py
MergeAccountingClient/api/invoices_api.py
MergeAccountingClient/api/issues_api.py
MergeAccountingClient/api/items_api.py
MergeAccountingClient/api/journal_entries_api.py
MergeAccountingClient/api/link_token_api.py
MergeAccountingClient/api/linked_accounts_api.py
MergeAccountingClient/api/passthrough_api.py
MergeAccountingClient/api/payments_api.py
MergeAccountingClient/api/phone_numbers_api.py
MergeAccountingClient/api/purchase_orders_api.py
MergeAccountingClient/api/regenerate_key_api.py
MergeAccountingClient/api/report_items_api.py
MergeAccountingClient/api/sync_status_api.py
MergeAccountingClient/api/tax_rates_api.py
MergeAccountingClient/api/tracking_categories_api.py
MergeAccountingClient/apis/__init__.py
MergeAccountingClient/model/__init__.py
MergeAccountingClient/model/account.py
MergeAccountingClient/model/account_details.py
MergeAccountingClient/model/account_details_and_actions.py
MergeAccountingClient/model/account_details_and_actions_integration.py
merge_accounting_client-1.0.2.dist-info/METADATA
merge_accounting_client-1.0.2.dist-info/WHEEL
merge_accounting_client-1.0.2.dist-info/top_level.txt
merge_accounting_client-1.0.2.dist-info/RECORD
