Metadata-Version: 2.1
Name: merge-accounting-client
Version: 1.0.2
Summary: Merge Accounting API
Home-page: UNKNOWN
Author: Merge Team
Author-email: hello@merge.dev
License: UNKNOWN
Keywords: OpenAPI,OpenAPI-Generator,Merge Accounting API
Platform: UNKNOWN
Requires-Python: >=3.6
Requires-Dist: urllib3 (>=1.25.3)
Requires-Dist: python-dateutil
